stubgen_pyx/__init__.py
stubgen_pyx/_version.py
stubgen_pyx/cli.py
stubgen_pyx/config.py
stubgen_pyx/stubgen.py
stubgen_pyx/analysis/__init__.py
stubgen_pyx/analysis/visitor.py
stubgen_pyx/builders/__init__.py
stubgen_pyx/builders/builder.py
stubgen_pyx/conversion/__init__.py
stubgen_pyx/conversion/conversion_utils.py
stubgen_pyx/conversion/converter.py
stubgen_pyx/conversion/signature.py
stubgen_pyx/models/__init__.py
stubgen_pyx/models/pyi_elements.py
stubgen_pyx/parsing/__init__.py
stubgen_pyx/parsing/file_parsing.py
stubgen_pyx/parsing/parser.py
stubgen_pyx/parsing/preprocess.py
stubgen_pyx/postprocessing/__init__.py
stubgen_pyx/postprocessing/collect_names.py
stubgen_pyx/postprocessing/deduplicate_imports.py
stubgen_pyx/postprocessing/epilog.py
stubgen_pyx/postprocessing/normalize_names.py
stubgen_pyx/postprocessing/pipeline.py
stubgen_pyx/postprocessing/sort_imports.py
stubgen_pyx/postprocessing/trim_imports.py
stubgen_pyx-0.2.1.dist-info/licenses/LICENSE
stubgen_pyx-0.2.1.dist-info/METADATA
stubgen_pyx-0.2.1.dist-info/WHEEL
stubgen_pyx-0.2.1.dist-info/entry_points.txt
stubgen_pyx-0.2.1.dist-info/top_level.txt
stubgen_pyx-0.2.1.dist-info/RECORD
