Metadata-Version: 2.4
Name: stubgen-pyx
Version: 0.2.1
Summary: Generates `.pyi` files from Cython modules in a given package directory.
Author: Jonathan Townsend
License: MIT License
Project-URL: Homepage, https://github.com/jon-edward/stubgen-pyx
Keywords: cython,stubgen,type stubs,pyi,type hints
Classifier: Programming Language :: Python :: 3
Classifier: License :: OSI Approved :: MIT License
Classifier: Operating System :: OS Independent
Requires-Python: >=3.9
License-File: LICENSE
Requires-Dist: Cython>=3.0.11
Requires-Dist: isort>=6.1.0
Provides-Extra: test
Requires-Dist: pytest>=7.4.0; extra == "test"
Dynamic: license-file
